CHANGELOG.rst
MANIFEST.in
README.rst
TODO
ZODB3.patch
neo.conf
setup.py
neo/__init__.py
neo/debug.py
neo/admin/__init__.py
neo/admin/app.py
neo/admin/handler.py
neo/client/Storage.py
neo/client/__init__.py
neo/client/app.py
neo/client/cache.py
neo/client/component.xml
neo/client/config.py
neo/client/exception.py
neo/client/iterator.py
neo/client/transactions.py
neo/client/zodburi.py
neo/client/handlers/__init__.py
neo/client/handlers/master.py
neo/client/handlers/storage.py
neo/lib/__init__.py
neo/lib/app.py
neo/lib/attributeTracker.py
neo/lib/bootstrap.py
neo/lib/compress.py
neo/lib/config.py
neo/lib/connection.py
neo/lib/connector.py
neo/lib/debug.py
neo/lib/dispatcher.py
neo/lib/event.py
neo/lib/exception.py
neo/lib/handler.py
neo/lib/interfaces.py
neo/lib/locking.py
neo/lib/logger.py
neo/lib/node.py
neo/lib/patch.py
neo/lib/protocol.py
neo/lib/pt.py
neo/lib/threaded_app.py
neo/lib/util.py
neo/master/__init__.py
neo/master/app.py
neo/master/backup_app.py
neo/master/pt.py
neo/master/recovery.py
neo/master/transactions.py
neo/master/verification.py
neo/master/handlers/__init__.py
neo/master/handlers/administration.py
neo/master/handlers/backup.py
neo/master/handlers/client.py
neo/master/handlers/identification.py
neo/master/handlers/master.py
neo/master/handlers/storage.py
neo/neoctl/__init__.py
neo/neoctl/app.py
neo/neoctl/handler.py
neo/neoctl/neoctl.py
neo/scripts/__init__.py
neo/scripts/neoadmin.py
neo/scripts/neoctl.py
neo/scripts/neolog.py
neo/scripts/neomaster.py
neo/scripts/neomigrate.py
neo/scripts/neostorage.py
neo/scripts/runner.py
neo/scripts/simple.py
neo/storage/__init__.py
neo/storage/app.py
neo/storage/checker.py
neo/storage/replicator.py
neo/storage/shared_queue.py
neo/storage/transactions.py
neo/storage/database/__init__.py
neo/storage/database/importer.py
neo/storage/database/manager.py
neo/storage/database/mysqldb.py
neo/storage/database/sqlite.py
neo/storage/handlers/__init__.py
neo/storage/handlers/client.py
neoppod.egg-info/PKG-INFO
neoppod.egg-info/SOURCES.txt
neoppod.egg-info/dependency_links.txt
neoppod.egg-info/entry_points.txt
neoppod.egg-info/requires.txt
neoppod.egg-info/top_level.txt
neoppod.egg-info/zip-safe
