Metadata-Version: 1.1
Name: neoppod
Version: 1.12.0
Summary: Distributed, redundant and transactional storage for ZODB
Home-page: https://neo.nexedi.com/
Author: Nexedi SA
Author-email: neo-dev@erp5.org
License: GPL 2+
Platform: any
Classifier: Framework :: ZODB
Classifier: Intended Audience :: Developers
Classifier: License :: OSI Approved :: GNU General Public License (GPL)
Classifier: Operating System :: POSIX :: Linux
Classifier: Programming Language :: Python :: 2.7
Classifier: Topic :: Database
Classifier: Topic :: Software Development :: Libraries :: Python Modules
